vio2/__init__.py
vio2/__main__.py
vio2-0.1.4.dist-info/LICENSE
vio2-0.1.4.dist-info/METADATA
vio2-0.1.4.dist-info/WHEEL
vio2-0.1.4.dist-info/top_level.txt
vio2-0.1.4.dist-info/RECORD
