Metadata-Version: 2.1
Name: vio2
Version: 0.1.4
Summary: Translator from Python to Russian pseudo-language and vice versa. Makes programming more accessible.
Home-page: https://github.com/kollieartwolf/violetta2
Author: titoffklim
Author-email: titoffklim@cclc.tech
License: UNKNOWN
Platform: UNKNOWN
Classifier: Programming Language :: Python :: 3
Classifier: License :: OSI Approved :: GNU General Public License v3 or later (GPLv3+)
Classifier: Operating System :: OS Independent
Requires-Python: >=3.8
